{
    "pools": [
        {
            "rolls": 1,
            "entries": [
                {
                    "type": "item",
                    "name": "potion",
                    "functions": [
                        {
                            "function": "set_name",
                            "name": {
                                "translate": "item.sco_items.madness_potion",
                                "fallback": "狂化のポーション",
                                "italic": false
                            }
                        },
                        {
                            "function": "set_components",
                            "components": {
                                "potion_contents": {
                                    "custom_color": 9899582,
                                    "custom_effects": [
                                        {
                                            "id": "unluck",
                                            "amplifier": 119,
                                            "duration": 10
                                        },
                                        {
                                            "id": "wither",
                                            "amplifier": 2,
                                            "duration": 300
                                        },
                                        {
                                            "id": "regeneration",
                                            "amplifier": 0,
                                            "duration": 80
                                        },
                                        {
                                            "id": "strength",
                                            "amplifier": 1,
                                            "duration": 300
                                        }
                                    ]
                                },
                                "max_stack_size": 4
                            }
                        }
                    ]
                }
            ]
        }
    ]
}
